{
  "refreshDuring": {
    "url": "https://woogoro.com/auto-repair.html?path=quote",
    "h1": "Auto Repair Pricing",
    "hasFileInput": true,
    "isInitial": false,
    "isStuckOnAnalyzing": false
  },
  "doubleUpload": {
    "outcome": "rendered",
    "bodyHead": "Skip to main content\n✓ Free · No email · No phone · No signup · We never sell or share your data\nWoogoro\nGuides\nMethodology\nAuto Repair Pricing\n\nWhether you're shopping around or checking a quote you already have.\n\n🔎 I Need an Estimate\n\nSee fair prices for your car and repair\n\n📄 I Have a Quote\n\nUpload your mechanic quote for AI analysis\n\n⚖ Compare 2-3 Quotes\n\nSide by side: price, parts, labor, w"
  }
}